pymermaiddiagram/__init__.py
pymermaiddiagram/pymermaid.py
pymermaiddiagram-0.0.3.dist-info/LICENSE.txt
pymermaiddiagram-0.0.3.dist-info/METADATA
pymermaiddiagram-0.0.3.dist-info/WHEEL
pymermaiddiagram-0.0.3.dist-info/top_level.txt
pymermaiddiagram-0.0.3.dist-info/RECORD
